AUTHORS
LICENSE
MANIFEST.in
README.md
setup.py
django_writing.egg-info/PKG-INFO
django_writing.egg-info/SOURCES.txt
django_writing.egg-info/dependency_links.txt
django_writing.egg-info/requires.txt
django_writing.egg-info/top_level.txt
writing/__init__.py
writing/admin.py
writing/mixins.py
writing/models.py
writing/querysets.py
writing/settings.py
writing/urls.py
writing/views.py
writing/locale/sk/LC_MESSAGES/django.mo
writing/locale/sk/LC_MESSAGES/django.po
writing/migrations/0001_initial.py
writing/migrations/0002_auto_20200608_1552.py
writing/migrations/0003_auto_20200608_1554.py
writing/migrations/0004_article_image.py
writing/migrations/0005_article_language.py
writing/migrations/0006_article_publish_date.py
writing/migrations/0007_markdown_to_html.py
writing/migrations/0008_html_field.py
writing/migrations/__init__.py
writing/templates/writing/article_detail.html
writing/templates/writing/article_list.html