Metadata-Version: 2.1
Name: django-writing
Version: 2.0.0
Summary: Basic blog app for Django
Home-page: https://github.com/PragmaticMates/django-writing
Author: Pragmatic Mates
Author-email: info@pragmaticmates.com
Maintainer: Pragmatic Mates
Maintainer-email: info@pragmaticmates.com
License: BSD License
Keywords: django blog article category writing
Classifier: Programming Language :: Python
Classifier: Programming Language :: Python :: 3.7
Classifier: Operating System :: OS Independent
Classifier: Environment :: Web Environment
Classifier: Intended Audience :: Developers
Classifier: Framework :: Django
Classifier: License :: OSI Approved :: BSD License
Classifier: Development Status :: 3 - Alpha
License-File: LICENSE
License-File: AUTHORS
Requires-Dist: django
Requires-Dist: markdown
Requires-Dist: martor
Requires-Dist: django-tinymce
